<?xml version="1.0" encoding="UTF-8" standalone="yes"?><store><name>MyStore</name><categories><name>Electronics</name><products><name>Laptop</name><price>999.99</price><expirationDate>2023-12-09</expirationDate><quantity>10</quantity></products><products><name>Smartphone</name><price>499.99</price><expirationDate>2023-12-09</expirationDate><quantity>20</quantity></products></categories><categories><name>Clothing</name><products><name>T-Shirt</name><price>19.99</price><expirationDate>2023-12-09</expirationDate><quantity>30</quantity></products><products><name>Jeans</name><price>49.99</price><expirationDate>2023-12-09</expirationDate><quantity>15</quantity></products></categories></store>